moneroblocks/__init__.py
moneroblocks/blockexplorer.py
moneroblocks/util.py
moneroblocks-0.0.1.dist-info/LICENSE
moneroblocks-0.0.1.dist-info/METADATA
moneroblocks-0.0.1.dist-info/WHEEL
moneroblocks-0.0.1.dist-info/top_level.txt
moneroblocks-0.0.1.dist-info/RECORD
