Metadata-Version: 2.1
Name: moneroblocks
Version: 0.0.1
Summary: API wrapper for moneroblocks.info
Home-page: http://github.com/pasquantonio/moneroblocks
Author: Joe Pasquantonio
Author-email: joepasquantonio@gmail.com
License: MIT
Platform: UNKNOWN
Requires-Python: >=3
Requires-Dist: requests
